ndbioimage/__init__.py
ndbioimage/jvm.py
ndbioimage/readers/__init__.py
ndbioimage/readers/bfread.py
ndbioimage/readers/cziread.py
ndbioimage/readers/fijiread.py
ndbioimage/readers/metaseriesread.py
ndbioimage/readers/ndread.py
ndbioimage/readers/seqread.py
ndbioimage/readers/tifread.py
ndbioimage/transform.txt
ndbioimage/transforms.py
ndbioimage-2026.1.2.dist-info/METADATA
ndbioimage-2026.1.2.dist-info/WHEEL
ndbioimage-2026.1.2.dist-info/entry_points.txt
ndbioimage-2026.1.2.dist-info/licenses/LICENSE
ndbioimage-2026.1.2.dist-info/RECORD
