Metadata-Version: 2.4
Name: ndbioimage
Version: 2026.1.2
Summary: Bio image reading, metadata and some affine registration.
License: GPL-3.0-or-later
License-File: LICENSE
Keywords: bioformats,imread,numpy,metadata
Author: W. Pomp
Author-email: w.pomp@nki.nl
Requires-Python: >=3.10
Classifier: License :: OSI Approved :: GNU General Public License v3 or later (GPLv3+)
Classifier: Programming Language :: Python :: 3
Classifier: Programming Language :: Python :: 3.10
Classifier: Programming Language :: Python :: 3.11
Classifier: Programming Language :: Python :: 3.12
Classifier: Programming Language :: Python :: 3.13
Classifier: Programming Language :: Python :: 3.14
Provides-Extra: bioformats
Provides-Extra: test
Provides-Extra: write
Requires-Dist: JPype1 ; extra == "bioformats"
Requires-Dist: SimpleITK-SimpleElastix ; sys_platform != "darwin"
Requires-Dist: czifile (==2019.7.2)
Requires-Dist: imagecodecs
Requires-Dist: lxml
Requires-Dist: matplotlib ; extra == "write"
Requires-Dist: numpy (>=1.20)
Requires-Dist: ome-types
Requires-Dist: pandas
Requires-Dist: parfor (>=2025.1.0)
Requires-Dist: pint
Requires-Dist: pytest ; extra == "test"
Requires-Dist: pyyaml
Requires-Dist: scikit-image
Requires-Dist: scikit-video ; extra == "write"
Requires-Dist: tifffile (<=2025.1.10)
Requires-Dist: tiffwrite (>=2024.12.1)
Requires-Dist: tqdm
Project-URL: Repository, https://github.com/wimpomp/ndbioimage
